vivid3d/__init__.py
vivid3d-0.0.1.dist-info/LICENSE
vivid3d-0.0.1.dist-info/METADATA
vivid3d-0.0.1.dist-info/WHEEL
vivid3d-0.0.1.dist-info/top_level.txt
vivid3d-0.0.1.dist-info/RECORD
