Metadata-Version: 2.1
Name: vivid3d
Version: 0.0.1
Summary: 3D visualization
Home-page: https://github.com/GalaxyHunters/Vivid
Author: The Galaxy Hunters IL
Author-email: galaxyhuntersil@gmail.com
License: UNKNOWN
Project-URL: Bug Tracker, https://github.com/GalaxyHunters/Vivid/issues
Platform: UNKNOWN
Classifier: Programming Language :: Python :: 2
Classifier: License :: OSI Approved :: MIT License
Classifier: Operating System :: OS Independent
Requires-Python: >=2.7
